LICENSE.md
MANIFEST.in
README.md
setup.py
sepa/__init__.py
sepa/builder.py
sepa/parser.py
sepa/signer.py
sepa/validator.py
sepa.egg-info/PKG-INFO
sepa.egg-info/SOURCES.txt
sepa.egg-info/dependency_links.txt
sepa.egg-info/requires.txt
sepa.egg-info/top_level.txt
sepa/definitions/__init__.py
sepa/definitions/general.py
sepa/definitions/mandate.py
sepa/definitions/payment.py
sepa/definitions/statement.py
sepa/messages/__init__.py
sepa/messages/camt/__init__.py
sepa/messages/camt/camt053.py
sepa/messages/pain/__init__.py
sepa/messages/pain/pain008.py
sepa/messages/pain/pain009.py
sepa/messages/pain/pain010.py
sepa/messages/pain/pain011.py
sepa/schemas/camt.052.001.06.xsd
sepa/schemas/camt.053.001.06.xsd
sepa/schemas/camt.054.001.06.xsd
sepa/schemas/camt.060.001.03.xsd
sepa/schemas/pain.001.001.08.xsd
sepa/schemas/pain.002.001.08.xsd
sepa/schemas/pain.007.001.07.xsd
sepa/schemas/pain.008.001.07.xsd
sepa/schemas/pain.009.001.05.xsd
sepa/schemas/pain.010.001.05.xsd
sepa/schemas/pain.011.001.05.xsd
sepa/schemas/pain.012.001.05.xsd
sepa/schemas/pain.017.001.01.xsd
sepa/schemas/pain.018.001.01.xsd
tests/__init__.py
tests/test.py
tests/util.py