Metadata-Version: 1.0
Name: sepa
Version: 0.5.0
Summary: Python library for parsing and building SEPA Direct Debit and SEPA eMandate schemas.
Home-page: https://github.com/VerenigingCampusKabel/python-sepa
Author: Vereniging Campus Kabel
Author-email: info@vck.utwente.nl
License: The MIT License (MIT)
